aims/__init__.py
aims/cli.py
aims/data_structures.py
aims/gui.py
aims/logbook_report.py
aims/output.py
aims/parse.py
aims/py.typed
aims/roster.py
aims/version.py
aims_convert-2.3.dist-info/LICENSE
aims_convert-2.3.dist-info/METADATA
aims_convert-2.3.dist-info/WHEEL
aims_convert-2.3.dist-info/entry_points.txt
aims_convert-2.3.dist-info/top_level.txt
aims_convert-2.3.dist-info/RECORD
