Metadata-Version: 2.1
Name: aims-convert
Version: 2.3
Summary: Extract useful information from AIMS
Home-page: https://github.com/JonHurst/aims-convert
Author: Jon Hurst
Author-email: jon.a@hursts.org.uk
Classifier: Development Status :: 4 - Beta
Classifier: Environment :: Console
Classifier: Programming Language :: Python :: 3
Classifier: License :: OSI Approved :: GNU General Public License v3 or later (GPLv3+)
Classifier: Operating System :: OS Independent
Requires-Python: >=3.11
License-File: LICENSE
Requires-Dist: nightflight
Requires-Dist: bs4
Requires-Dist: html5lib
Provides-Extra: unit-tests
Requires-Dist: freezegun; extra == "unit-tests"
